{"cameraMode":{"drawMode":0,"name":"Shaded","section":"Shading Mode"},"sceneLighting":true,"audioPlay":false,"sceneViewState":{"m_AlwaysRefresh":false,"showFog":false,"showSkybox":true,"showFlares":true,"showImageEffects":true,"showParticleSystems":true,"showVisualEffectGraphs":true,"m_FxEnabled":true},"in2DMode":false,"pivot":{"x":52.21285629272461,"y":-59.62620162963867,"z":133.8750457763672},"rotation":{"x":0.1690431535243988,"y":-0.4032471477985382,"z":0.07807312905788422,"w":0.8963328003883362},"size":157.98574829101563,"orthographic":false}